parsivar/__init__.py
parsivar/chunker.py
parsivar/data_helper.py
parsivar/dependency.py
parsivar/normalizer.py
parsivar/postagger.py
parsivar/spell_checker.py
parsivar/stemmer.py
parsivar/token_merger.py
parsivar/tokenizer.py
parsivar/resource/dependency_parser/maltparser-1.9.2.jar
parsivar/resource/dependency_parser/total_dep_parser.mco
parsivar/resource/dependency_parser/lib/liblinear-1.8.jar
parsivar/resource/dependency_parser/lib/libsvm.jar
parsivar/resource/dependency_parser/lib/log4j.jar
parsivar/resource/normalizer/Dic1_new.txt
parsivar/resource/normalizer/Dic2_new.txt
parsivar/resource/normalizer/Dic3_new.txt
parsivar/resource/postagger/UPC_full_model_wapiti
parsivar/resource/postagger/stanford-postagger.jar
parsivar/resource/stemmer/mokasar.txt
parsivar/resource/stemmer/pasvand.txt
parsivar/resource/stemmer/pishvand.txt
parsivar/resource/stemmer/stem_irregularNounDict.pckl
parsivar/resource/stemmer/stem_lex.pckl
parsivar/resource/stemmer/stem_verbMap.pckl
parsivar/resource/stemmer/verbStemDict.pckl
parsivar/resource/stemmer/verb_tense.txt
parsivar/resource/tokenizer/TokenMerger.pckl
parsivar/resource/tokenizer/enDict
parsivar/resource/tokenizer/faDict
parsivar-0.2.3.1.dist-info/LICENSE.txt
parsivar-0.2.3.1.dist-info/METADATA
parsivar-0.2.3.1.dist-info/WHEEL
parsivar-0.2.3.1.dist-info/top_level.txt
parsivar-0.2.3.1.dist-info/RECORD
